{
  "entrypoints": {
    "admin": {
      "css": [
        "/bundles/talavweb/admin.css?bba4765cfd3411c63972"
      ],
      "js": [
        "/bundles/talavweb/admin.js?61bee77cfca91a1d1c84"
      ]
    },
    "event_details": {
      "js": [
        "/bundles/talavweb/event_details.js?fc7b6ddb9130e581e136"
      ]
    },
    "app": {
      "css": [
        "/bundles/talavweb/app.css?216229890b41c38acd5b"
      ],
      "js": [
        "/bundles/talavweb/app.js?9630f1d6935c8cda8fae"
      ]
    }
  }
}